toehold/__init__.py
toehold/optimize.py
toehold/precdict.py
toehold/train.py
toehold/utils.py
toehold-0.0.1.dist-info/LICENSE
toehold-0.0.1.dist-info/METADATA
toehold-0.0.1.dist-info/WHEEL
toehold-0.0.1.dist-info/top_level.txt
toehold-0.0.1.dist-info/zip-safe
toehold-0.0.1.dist-info/RECORD
